aoe2de_rms_gen_obj_parser/__init__.py
aoe2de_rms_gen_obj_parser/blocks.py
aoe2de_rms_gen_obj_parser/const.py
aoe2de_rms_gen_obj_parser/genobj.py
aoe2de_rms_gen_obj_parser/parsers.py
aoe2de_rms_gen_obj_parser-2.1.1.dist-info/LICENSE
aoe2de_rms_gen_obj_parser-2.1.1.dist-info/METADATA
aoe2de_rms_gen_obj_parser-2.1.1.dist-info/WHEEL
aoe2de_rms_gen_obj_parser-2.1.1.dist-info/top_level.txt
aoe2de_rms_gen_obj_parser-2.1.1.dist-info/RECORD
