Metadata-Version: 2.1
Name: aoe2de-rms-gen-obj-parser
Version: 2.1.1
Summary: aoe2de_rms_gen_obj_parser is a python package to parser Age of Empires2: Definitive Edition RMS
Home-page: https://github.com/gfruleux/aoe2de_rms_genobj_parser
Author: Grégoire Fruleux
Author-email: gregoire.fruleux.pro@gmail.com
License: MIT
Platform: UNKNOWN
Classifier: Development Status :: 5 - Production/Stable
Classifier: License :: OSI Approved :: MIT License
Classifier: Programming Language :: Python
Classifier: Programming Language :: Python :: 3.8
Classifier: Topic :: Software Development :: Libraries
Classifier: Topic :: Software Development :: Libraries :: Python Modules
Classifier: Intended Audience :: Developers
Requires-Python: >=3.8.1
Requires-Dist: requests
